LICENSE
README.md
setup.cfg
setup.py
ddnet_parser/__init__.py
ddnet_parser/parser.py
ddnet_parser.egg-info/PKG-INFO
ddnet_parser.egg-info/SOURCES.txt
ddnet_parser.egg-info/dependency_links.txt
ddnet_parser.egg-info/top_level.txt
ddnet_parser/parsers/__init__.py
ddnet_parser/parsers/clients.py
ddnet_parser/parsers/maps.py
ddnet_parser/parsers/playerstats.py
ddnet_parser/parsers/profile.py
ddnet_parser/parsers/servers.py
ddnet_parser/parsers/utils.py