Metadata-Version: 2.4
Name: ddnet_parser
Version: 1.3.0
Summary: Simple data parser from ddnet sites
Home-page: https://github.com/neyxezz/ddnet-parser
Author: neyxezz
Author-email: bassboosthelp@gmail.com
Classifier: Programming Language :: Python :: 3
Classifier: License :: Public Domain
Classifier: Operating System :: OS Independent
Requires-Python: >=3.8
License-File: LICENSE
Dynamic: author
Dynamic: author-email
Dynamic: classifier
Dynamic: description
Dynamic: description-content-type
Dynamic: home-page
Dynamic: license-file
Dynamic: requires-python
Dynamic: summary
